thymus_ast/__init__.py
thymus_ast/ios/__init__.py
thymus_ast/ios/ios.py
thymus_ast/junos/__init__.py
thymus_ast/junos/junos.py
thymus_ast/junos_ng/__init__.py
thymus_ast/junos_ng/junos_ng.py
thymus_ast-0.1.8.2.dist-info/LICENSE
thymus_ast-0.1.8.2.dist-info/METADATA
thymus_ast-0.1.8.2.dist-info/WHEEL
thymus_ast-0.1.8.2.dist-info/RECORD
