Metadata-Version: 2.1
Name: thymus-ast
Version: 0.1.8.2
Summary: A set of tools to build ASTs for different NOS
Author: Igor Malyushkin
Author-email: gmalyushkin@gmail.com
Requires-Python: >=3.9,<4.0
Classifier: Programming Language :: Python :: 3
Classifier: Programming Language :: Python :: 3.9
Classifier: Programming Language :: Python :: 3.10
Classifier: Programming Language :: Python :: 3.11
Classifier: Programming Language :: Python :: 3.12
